[
  {
    "id": "fungal_inheritance",
    "title": "Fungal Inheritance",
    "description": "Carries a portion of each city's fungal production forward.",
    "applyRules": [
      {
        "type": "addHomogeneousValue",
        "stateKey": "fungiBonus",
        "valueId": "resource.fungi",
        "valueField": "produced",
        "multiplier": 0.1
      }
    ],
    "effects": [
      {
        "valueId": "resource.fungi",
        "additionalKeywords": [
          "production"
        ],
        "additive": {
          "stateKey": "fungiBonus"
        },
        "multiplier": 1
      }
    ]
  },
  {
    "id": "tiny_settlement",
    "title": "Tiny settlement",
    "description": "Merely an outpost not even a village. Easy to blend with environment. Sieges will be much shorter.",
    "applyRules": [],
    "effects": [
      {
        "valueId": "siege.lengthMultiplier",
        "multiplier": 0.2
      }
    ]
  }
]
